README.md
setup.py
aiopo/_PushoverClient.py
aiopo/__init__.py
aiopo.egg-info/PKG-INFO
aiopo.egg-info/SOURCES.txt
aiopo.egg-info/dependency_links.txt
aiopo.egg-info/requires.txt
aiopo.egg-info/top_level.txt